FederatedDataset/PartitionTypes/iid_partition.py
FederatedDataset/PartitionTypes/majority_minority_partition.py
FederatedDataset/PartitionTypes/non_iid_partition.py
FederatedDataset/PartitionTypes/non_iid_partition_nodes.py
FederatedDataset/PartitionTypes/non_iid_partition_nodes_with_sensitive_feature.py
FederatedDataset/PartitionTypes/non_iid_partition_public_private.py
FederatedDataset/PartitionTypes/non_iid_partition_with_sensitive_feature.py
FederatedDataset/PartitionTypes/percentage_partition.py
FederatedDataset/PartitionTypes/unbalanced_partition.py
FederatedDataset/PartitionTypes/unbalanced_partition_one_class.py
FederatedDataset/Utils/__init__.py
FederatedDataset/Utils/custom_dataset.py
FederatedDataset/Utils/dataset_downloader.py
FederatedDataset/Utils/lda.py
FederatedDataset/Utils/preferences.py
FederatedDataset/Utils/storage_manager.py
FederatedDataset/Utils/utils.py
FederatedDataset/__init__.py
FederatedDataset/partition_dataset.py
pistacchio_federated_dataset-0.0.1.post18.dist-info/METADATA
pistacchio_federated_dataset-0.0.1.post18.dist-info/WHEEL
pistacchio_federated_dataset-0.0.1.post18.dist-info/RECORD
