Metadata-Version: 2.1
Name: pistacchio-federated-dataset
Version: 0.0.1.post18
Summary: A simple library to partition your dataset to perform federated learning
License: MIT
Author: Luca Corbucci
Requires-Python: >=3.8,<4.0
Classifier: License :: OSI Approved :: MIT License
Classifier: Programming Language :: Python :: 3
Classifier: Programming Language :: Python :: 3.8
Classifier: Programming Language :: Python :: 3.9
Classifier: Programming Language :: Python :: 3.10
Classifier: Programming Language :: Python :: 3.11
Requires-Dist: black (>=23.3.0,<24.0.0)
Requires-Dist: google-api-python-client (>=2.86.0,<3.0.0)
Requires-Dist: numpy (>=1.24.2,<2.0.0)
Requires-Dist: opacus (==1.3)
Requires-Dist: pandas (>=1.5.3,<2.0.0)
Requires-Dist: pytest (>=7.2.2,<8.0.0)
Requires-Dist: scikit-learn (>=1.2.2,<2.0.0)
Requires-Dist: torch (==2.0.0)
Requires-Dist: torchvision (>=0.15.1,<0.16.0)
Requires-Dist: tqdm (>=4.65.0,<5.0.0)
Requires-Dist: wandb (>=0.14.0,<0.15.0)
